odoo10_addon_website_event_type_description-10.0.1.1.0-py2.7-nspkg.pth
odoo/addons/website_event_type_description/README.rst
odoo/addons/website_event_type_description/__init__.py
odoo/addons/website_event_type_description/__manifest__.py
odoo/addons/website_event_type_description/i18n/es.po
odoo/addons/website_event_type_description/images/all.png
odoo/addons/website_event_type_description/images/seminars.png
odoo/addons/website_event_type_description/models/__init__.py
odoo/addons/website_event_type_description/models/event.py
odoo/addons/website_event_type_description/static/description/icon.png
odoo/addons/website_event_type_description/views/event.xml
odoo/addons/website_event_type_description/views/event_type_view.xml
odoo10_addon_website_event_type_description-10.0.1.1.0.dist-info/DESCRIPTION.rst
odoo10_addon_website_event_type_description-10.0.1.1.0.dist-info/METADATA
odoo10_addon_website_event_type_description-10.0.1.1.0.dist-info/RECORD
odoo10_addon_website_event_type_description-10.0.1.1.0.dist-info/WHEEL
odoo10_addon_website_event_type_description-10.0.1.1.0.dist-info/metadata.json
odoo10_addon_website_event_type_description-10.0.1.1.0.dist-info/namespace_packages.txt
odoo10_addon_website_event_type_description-10.0.1.1.0.dist-info/top_level.txt
